odoo8_addon_l10n_us_form_1099-8.0.1.0.0-py2.7-nspkg.pth
odoo8_addon_l10n_us_form_1099-8.0.1.0.0.dist-info/DESCRIPTION.rst
odoo8_addon_l10n_us_form_1099-8.0.1.0.0.dist-info/METADATA
odoo8_addon_l10n_us_form_1099-8.0.1.0.0.dist-info/RECORD
odoo8_addon_l10n_us_form_1099-8.0.1.0.0.dist-info/WHEEL
odoo8_addon_l10n_us_form_1099-8.0.1.0.0.dist-info/metadata.json
odoo8_addon_l10n_us_form_1099-8.0.1.0.0.dist-info/namespace_packages.txt
odoo8_addon_l10n_us_form_1099-8.0.1.0.0.dist-info/top_level.txt
odoo_addons/l10n_us_form_1099/README.rst
odoo_addons/l10n_us_form_1099/__init__.py
odoo_addons/l10n_us_form_1099/__openerp__.py
odoo_addons/l10n_us_form_1099/models/__init__.py
odoo_addons/l10n_us_form_1099/models/res_partner.py
odoo_addons/l10n_us_form_1099/static/description/l10n_us_form_1099.png
odoo_addons/l10n_us_form_1099/static/description/l10n_us_form_1099.svg
odoo_addons/l10n_us_form_1099/views/res_partner.xml
