Metadata-Version: 2.0
Name: odoo8-addon-l10n-us-form-1099
Version: 8.0.1.0.0
Summary: Add 1099 field to res.partner that will auto-check supplier
Home-page: http://www.ursainfosystems.com
Author: Ursa Information Systems, Odoo Community Association (OCA)
Author-email: support@odoo-community.org
License: AGPL-3
Platform: UNKNOWN
Classifier: Programming Language :: Python
Classifier: Framework :: Odoo
Classifier: License :: OSI Approved :: GNU Affero General Public License v3
Requires-Python: ~=2.7
Requires-Dist: odoo (<9.0a,>=8.0a)
